better_notion_mcp/__init__.py
better_notion_mcp-0.1.3.dist-info/METADATA
better_notion_mcp-0.1.3.dist-info/WHEEL
better_notion_mcp-0.1.3.dist-info/RECORD
