Metadata-Version: 2.4
Name: better-notion-mcp
Version: 0.1.3
Summary: DEPRECATED: Please install 'engram-mcp' instead.
Project-URL: Repository, https://github.com/shubhamomar/engram-mcp
Author-email: Shubham Omar <shubhamomar53@gmail.com>
License: MIT
Requires-Python: >=3.10
Requires-Dist: engram-mcp
